httpstreamproxy/__init__.py
httpstreamproxy/app.py
httpstreamproxy/httpproxy.py
httpstreamproxy-0.1.6.dist-info/LICENSE
httpstreamproxy-0.1.6.dist-info/METADATA
httpstreamproxy-0.1.6.dist-info/WHEEL
httpstreamproxy-0.1.6.dist-info/entry_points.txt
httpstreamproxy-0.1.6.dist-info/top_level.txt
httpstreamproxy-0.1.6.dist-info/RECORD
