Metadata-Version: 2.1
Name: httpstreamproxy
Version: 0.1.6
Summary: A http stream proxy
Home-page: https://github.com/grro/httpstreamproxy
Author: Gregor Roth
Author-email: gregor.roth@web.de
License: MIT
Keywords: http,proxy,stream,server
Platform: UNKNOWN
Classifier: Programming Language :: Python :: 3
Classifier: License :: OSI Approved :: Apache Software License
Classifier: Operating System :: OS Independent
Classifier: Development Status :: 3 - Alpha
Requires-Dist: requests
